iracingdataapi/__init__.py
iracingdataapi/client.py
iracingdataapi/exceptions.py
iracingdataapi-1.3.0.dist-info/licenses/LICENSE
iracingdataapi-1.3.0.dist-info/METADATA
iracingdataapi-1.3.0.dist-info/WHEEL
iracingdataapi-1.3.0.dist-info/top_level.txt
iracingdataapi-1.3.0.dist-info/RECORD
