Metadata-Version: 2.4
Name: iracingdataapi
Version: 1.3.0
Summary: A simple wrapper around the iRacing General Data API
Home-page: https://github.com/jasondilworth56/iracingdataapi
Author: Jason Dilworth
Author-email: hello@jasondilworth.co.uk
Project-URL: Bug Tracker, https://github.com/jasondilworth56/iracingdataapi/issues
Classifier: Programming Language :: Python :: 3
Classifier: License :: OSI Approved :: MIT License
Classifier: Operating System :: OS Independent
Requires-Python: >=3.6
License-File: LICENSE
Requires-Dist: requests
Dynamic: author
Dynamic: author-email
Dynamic: classifier
Dynamic: description
Dynamic: description-content-type
Dynamic: home-page
Dynamic: license-file
Dynamic: project-url
Dynamic: requires-dist
Dynamic: requires-python
Dynamic: summary
